[
    {
        "UserID": 5984310,
        "FirstName": "Haerat",
        "LastName": "Alabi",
        "PublishUserProfile": true,
        "LargeFileName": "large_user5984310_4317216_202.jpg",
        "Email": "ha4407@trevor.org",
        "EmailBad": false,
        "PublishEmail": true,
        "MyContactsID": 0,
        "HasRelationships": false,
        "GradYear": "2024",
        "Grade": "",
        "GradeDisplay": "Twelfth",
        "Department": "",
        "SpouseID": 0,
        "GradeNumeric": 0,
        "GradeNumericDisplay": "12",
        "TotalCount": 74,
        "Deceased": false,
        "IsStudentInd": false,
        "PreferredAddressId": 4648745,
        "PreferredAddressLat": 0.0,
        "PreferredAddressLng": 0.0,
        "JobTitle": ""
    },
    {
        "UserID": 2663753,
        "FirstName": "Samuel",
        "LastName": "Asner",
        "PublishUserProfile": true,
        "LargeFileName": "large_user2663753_1091056_33.jpg",
        "Email": "sa2936@trevor.org",
        "EmailBad": false,
        "PublishEmail": true,
        "MyContactsID": 0,
        "HasRelationships": false,
        "Nickname": "Sam",
        "GradYear": "2024",
        "Grade": "",
        "GradeDisplay": "Twelfth",
        "Department": "",
        "SpouseID": 0,
        "GradeNumeric": 0,
        "GradeNumericDisplay": "12",
        "TotalCount": 0,
        "Deceased": false,
        "IsStudentInd": false,
        "PreferredAddressId": 1793343,
        "PreferredAddressLat": 0.0,
        "PreferredAddressLng": 0.0,
        "JobTitle": ""
    },
    {
        "UserID": 2663755,
        "FirstName": "Anthony",
        "LastName": "Bacidore",
        "PublishUserProfile": true,
        "LargeFileName": "large_user2663755_1091057_667.jpg",
        "Email": "ab3008@trevor.org",
        "EmailBad": false,
        "PublishEmail": true,
        "MyContactsID": 0,
        "HasRelationships": false,
        "GradYear": "2024",
        "Grade": "",
        "GradeDisplay": "Twelfth",
        "Department": "",
        "SpouseID": 0,
        "GradeNumeric": 0,
        "GradeNumericDisplay": "12",
        "TotalCount": 0,
        "Deceased": false,
        "IsStudentInd": false,
        "PreferredAddressId": 2006923,
        "PreferredAddressLat": 0.0,
        "PreferredAddressLng": 0.0,
        "JobTitle": ""
    },
    {
        "UserID": 5984315,
        "FirstName": "Haydn",
        "LastName": "Badini",
        "PublishUserProfile": true,
        "LargeFileName": "large_user5984315_4317221_731.jpg",
        "Email": "hb4414@trevor.org",
        "EmailBad": false,
        "PublishEmail": true,
        "MyContactsID": 0,
        "HasRelationships": false,
        "Nickname": "Haydn",
        "GradYear": "2024",
        "Grade": "",
        "GradeDisplay": "Twelfth",
        "Department": "",
        "SpouseID": 0,
        "GradeNumeric": 0,
        "GradeNumericDisplay": "12",
        "TotalCount": 0,
        "Deceased": false,
        "IsStudentInd": false,
        "PreferredAddressId": 4649333,
        "PreferredAddressLat": 0.0,
        "PreferredAddressLng": 0.0,
        "JobTitle": ""
    },
    {
        "UserID": 4397352,
        "FirstName": "Fanta",
        "LastName": "Bauer",
        "PublishUserProfile": true,
        "LargeFileName": "large_user4397352_2732705_12.jpg",
        "Email": "fb4016@trevor.org",
        "EmailBad": false,
        "PublishEmail": true,
        "MyContactsID": 0,
        "HasRelationships": false,
        "Nickname": "Fanta",
        "GradYear": "2024",
        "Grade": "",
        "GradeDisplay": "Twelfth",
        "Department": "",
        "SpouseID": 0,
        "GradeNumeric": 0,
        "GradeNumericDisplay": "12",
        "TotalCount": 0,
        "Deceased": false,
        "IsStudentInd": false,
        "PreferredAddressId": 2554934,
        "PreferredAddressLat": 0.0,
        "PreferredAddressLng": 0.0,
        "JobTitle": ""
    },
    {
        "UserID": 5984318,
        "FirstName": "Elizabeth",
        "LastName": "Baum",
        "PublishUserProfile": true,
        "LargeFileName": "large_user5984318_4317224_371.jpg",
        "Email": "eb4354@trevor.org",
        "EmailBad": false,
        "PublishEmail": true,
        "MyContactsID": 0,
        "HasRelationships": false,
        "Nickname": "Lizzie",
        "GradYear": "2024",
        "Grade": "",
        "GradeDisplay": "Twelfth",
        "Department": "",
        "SpouseID": 0,
        "GradeNumeric": 0,
        "GradeNumericDisplay": "12",
        "TotalCount": 0,
        "Deceased": false,
        "IsStudentInd": false,
        "PreferredAddressId": 4488799,
        "PreferredAddressLat": 0.0,
        "PreferredAddressLng": 0.0,
        "JobTitle": ""
    },
    {
        "UserID": 6444316,
        "FirstName": "Reese",
        "LastName": "Binder",
        "PublishUserProfile": true,
        "LargeFileName": "large_user6444316_4776572_815.jpg",
        "Email": "rb4634@trevor.org",
        "EmailBad": false,
        "PublishEmail": true,
        "MyContactsID": 0,
        "HasRelationships": false,
        "Nickname": "Reese",
        "GradYear": "2024",
        "Grade": "",
        "GradeDisplay": "Twelfth",
        "Department": "",
        "SpouseID": 0,
        "GradeNumeric": 0,
        "GradeNumericDisplay": "12",
        "TotalCount": 0,
        "Deceased": false,
        "IsStudentInd": false,
        "PreferredAddressId": 2006940,
        "PreferredAddressLat": 0.0,
        "PreferredAddressLng": 0.0,
        "JobTitle": ""
    },
    {
        "UserID": 2833315,
        "FirstName": "Harry",
        "LastName": "Blittner",
        "PublishUserProfile": true,
        "LargeFileName": "large_user2833315_1242215_115.jpg",
        "Email": "hb3261@trevor.org",
        "EmailBad": false,
        "PublishEmail": true,
        "MyContactsID": 0,
        "HasRelationships": false,
        "GradYear": "2024",
        "Grade": "",
        "GradeDisplay": "Twelfth",
        "Department": "",
        "SpouseID": 0,
        "GradeNumeric": 0,
        "GradeNumericDisplay": "12",
        "TotalCount": 0,
        "Deceased": false,
        "IsStudentInd": false,
        "PreferredAddressId": 1793409,
        "PreferredAddressLat": 0.0,
        "PreferredAddressLng": 0.0,
        "JobTitle": ""
    },
    {
        "UserID": 2833317,
        "FirstName": "Luke",
        "LastName": "Blumberg",
        "PublishUserProfile": true,
        "LargeFileName": "large_user2833317_1242216_656.jpg",
        "Email": "lb3264@trevor.org",
        "EmailBad": false,
        "PublishEmail": true,
        "MyContactsID": 0,
        "HasRelationships": false,
        "GradYear": "2024",
        "Grade": "",
        "GradeDisplay": "Twelfth",
        "Department": "",
        "SpouseID": 0,
        "GradeNumeric": 0,
        "GradeNumericDisplay": "12",
        "TotalCount": 0,
        "Deceased": false,
        "IsStudentInd": false,
        "PreferredAddressId": 2128396,
        "PreferredAddressLat": 0.0,
        "PreferredAddressLng": 0.0,
        "JobTitle": ""
    },
    {
        "UserID": 4397361,
        "FirstName": "Naomi",
        "LastName": "Butler",
        "PublishUserProfile": true,
        "LargeFileName": "large_user4397361_2732714_674.jpg",
        "Email": "nb4002@trevor.org",
        "EmailBad": false,
        "PublishEmail": true,
        "MyContactsID": 0,
        "HasRelationships": false,
        "Nickname": "Naomi",
        "GradYear": "2024",
        "Grade": "",
        "GradeDisplay": "Twelfth",
        "Department": "",
        "SpouseID": 0,
        "GradeNumeric": 0,
        "GradeNumericDisplay": "12",
        "TotalCount": 0,
        "Deceased": false,
        "IsStudentInd": false,
        "PreferredAddressId": 3243889,
        "PreferredAddressLat": 0.0,
        "PreferredAddressLng": 0.0,
        "JobTitle": ""
    },
    {
        "UserID": 2728482,
        "FirstName": "Gwyneth",
        "LastName": "Chu",
        "PublishUserProfile": true,
        "LargeFileName": "large_user2728482_1147070_521.jpg",
        "Email": "gc3153@trevor.org",
        "EmailBad": false,
        "PublishEmail": true,
        "MyContactsID": 0,
        "HasRelationships": false,
        "GradYear": "2024",
        "Grade": "",
        "GradeDisplay": "Twelfth",
        "Department": "",
        "SpouseID": 0,
        "GradeNumeric": 0,
        "GradeNumericDisplay": "12",
        "TotalCount": 0,
        "Deceased": false,
        "IsStudentInd": false,
        "PreferredAddressId": 1793508,
        "PreferredAddressLat": 0.0,
        "PreferredAddressLng": 0.0,
        "JobTitle": ""
    },
    {
        "UserID": 2833323,
        "FirstName": "Jordan",
        "LastName": "Crespin",
        "PublishUserProfile": true,
        "LargeFileName": "large_user2833323_1242222_649.jpg",
        "Email": "jc3233@trevor.org",
        "EmailBad": false,
        "PublishEmail": true,
        "MyContactsID": 0,
        "HasRelationships": false,
        "GradYear": "2024",
        "Grade": "",
        "GradeDisplay": "Twelfth",
        "Department": "",
        "SpouseID": 0,
        "GradeNumeric": 0,
        "GradeNumericDisplay": "12",
        "TotalCount": 0,
        "Deceased": false,
        "IsStudentInd": false,
        "PreferredAddressId": 2128408,
        "PreferredAddressLat": 0.0,
        "PreferredAddressLng": 0.0,
        "JobTitle": ""
    },
    {
        "UserID": 2728499,
        "FirstName": "Binita",
        "LastName": "Dasani",
        "PublishUserProfile": true,
        "LargeFileName": "large_user2728499_1147083_277.jpg",
        "Email": "bd3119@trevor.org",
        "EmailBad": false,
        "PublishEmail": true,
        "MyContactsID": 0,
        "HasRelationships": false,
        "GradYear": "2024",
        "Grade": "",
        "GradeDisplay": "Twelfth",
        "Department": "",
        "SpouseID": 0,
        "GradeNumeric": 0,
        "GradeNumericDisplay": "12",
        "TotalCount": 0,
        "Deceased": false,
        "IsStudentInd": false,
        "PreferredAddressId": 2052584,
        "PreferredAddressLat": 0.0,
        "PreferredAddressLng": 0.0,
        "JobTitle": ""
    },
    {
        "UserID": 2728502,
        "FirstName": "Krish",
        "LastName": "Dasani",
        "PublishUserProfile": true,
        "LargeFileName": "large_user2728502_1147086_423.jpg",
        "Email": "kd3120@trevor.org",
        "EmailBad": false,
        "PublishEmail": true,
        "MyContactsID": 0,
        "HasRelationships": false,
        "GradYear": "2024",
        "Grade": "",
        "GradeDisplay": "Twelfth",
        "Department": "",
        "SpouseID": 0,
        "GradeNumeric": 0,
        "GradeNumericDisplay": "12",
        "TotalCount": 0,
        "Deceased": false,
        "IsStudentInd": false,
        "PreferredAddressId": 2052584,
        "PreferredAddressLat": 0.0,
        "PreferredAddressLng": 0.0,
        "JobTitle": ""
    },
    {
        "UserID": 2833331,
        "FirstName": "Ella",
        "LastName": "Dragseth",
        "PublishUserProfile": true,
        "LargeFileName": "large_user2833331_1242226_875.jpg",
        "Email": "ed3266@trevor.org",
        "EmailBad": false,
        "PublishEmail": true,
        "MyContactsID": 0,
        "HasRelationships": false,
        "GradYear": "2024",
        "Grade": "",
        "GradeDisplay": "Twelfth",
        "Department": "",
        "SpouseID": 0,
        "GradeNumeric": 0,
        "GradeNumericDisplay": "12",
        "TotalCount": 0,
        "Deceased": false,
        "IsStudentInd": false,
        "PreferredAddressId": 4397769,
        "PreferredAddressLat": 0.0,
        "PreferredAddressLng": 0.0,
        "JobTitle": ""
    },
    {
        "UserID": 2833336,
        "FirstName": "Grant",
        "LastName": "Fesenmyer",
        "PublishUserProfile": true,
        "LargeFileName": "large_user2833336_1242230_24.jpg",
        "Email": "gf3242@trevor.org",
        "EmailBad": false,
        "PublishEmail": true,
        "MyContactsID": 0,
        "HasRelationships": false,
        "GradYear": "2024",
        "Grade": "",
        "GradeDisplay": "Twelfth",
        "Department": "",
        "SpouseID": 0,
        "GradeNumeric": 0,
        "GradeNumericDisplay": "12",
        "TotalCount": 0,
        "Deceased": false,
        "IsStudentInd": false,
        "PreferredAddressId": 1793677,
        "PreferredAddressLat": 0.0,
        "PreferredAddressLng": 0.0,
        "JobTitle": ""
    },
    {
        "UserID": 4397367,
        "FirstName": "Nicholas",
        "LastName": "Finkielstein",
        "PublishUserProfile": true,
        "LargeFileName": "large_user4397367_2732720_241.jpg",
        "Email": "nf4015@trevor.org",
        "EmailBad": false,
        "PublishEmail": true,
        "MyContactsID": 0,
        "HasRelationships": false,
        "Nickname": "Nick",
        "GradYear": "2024",
        "Grade": "",
        "GradeDisplay": "Twelfth",
        "Department": "",
        "SpouseID": 0,
        "GradeNumeric": 0,
        "GradeNumericDisplay": "12",
        "TotalCount": 0,
        "Deceased": false,
        "IsStudentInd": false,
        "PreferredAddressId": 3243894,
        "PreferredAddressLat": 0.0,
        "PreferredAddressLng": 0.0,
        "JobTitle": ""
    },
    {
        "UserID": 5984329,
        "FirstName": "Charles",
        "LastName": "Fishman",
        "PublishUserProfile": true,
        "LargeFileName": "large_user5984329_4317235_901.jpg",
        "Email": "cf4380@trevor.org",
        "EmailBad": false,
        "PublishEmail": true,
        "MyContactsID": 0,
        "HasRelationships": false,
        "Nickname": "Charlie",
        "GradYear": "2024",
        "Grade": "",
        "GradeDisplay": "Twelfth",
        "Department": "",
        "SpouseID": 0,
        "GradeNumeric": 0,
        "GradeNumericDisplay": "12",
        "TotalCount": 0,
        "Deceased": false,
        "IsStudentInd": false,
        "PreferredAddressId": 4648768,
        "PreferredAddressLat": 0.0,
        "PreferredAddressLng": 0.0,
        "JobTitle": ""
    },
    {
        "UserID": 5984334,
        "FirstName": "Josephine",
        "LastName": "Freiin von Girsewald",
        "PublishUserProfile": true,
        "Email": "jv4417@trevor.org",
        "EmailBad": false,
        "PublishEmail": true,
        "MyContactsID": 0,
        "HasRelationships": false,
        "Nickname": "Josephine",
        "GradYear": "2024",
        "Grade": "",
        "GradeDisplay": "Twelfth",
        "Department": "",
        "SpouseID": 0,
        "GradeNumeric": 0,
        "GradeNumericDisplay": "12",
        "TotalCount": 0,
        "Deceased": false,
        "IsStudentInd": false,
        "PreferredAddressId": 4649337,
        "PreferredAddressLat": 0.0,
        "PreferredAddressLng": 0.0,
        "JobTitle": ""
    },
    {
        "UserID": 5984337,
        "FirstName": "Max",
        "LastName": "Freud",
        "PublishUserProfile": true,
        "LargeFileName": "large_user5984337_4317243_712.jpg",
        "Email": "mf4418@trevor.org",
        "EmailBad": false,
        "PublishEmail": true,
        "MyContactsID": 0,
        "HasRelationships": false,
        "Nickname": "Max",
        "GradYear": "2024",
        "Grade": "",
        "GradeDisplay": "Twelfth",
        "Department": "",
        "SpouseID": 0,
        "GradeNumeric": 0,
        "GradeNumericDisplay": "12",
        "TotalCount": 0,
        "Deceased": false,
        "IsStudentInd": false,
        "PreferredAddressId": 4648774,
        "PreferredAddressLat": 0.0,
        "PreferredAddressLng": 0.0,
        "JobTitle": ""
    },
    {
        "UserID": 2663778,
        "FirstName": "Anthony",
        "LastName": "Galiotos",
        "PublishUserProfile": true,
        "LargeFileName": "large_user2663778_1091073_342.jpg",
        "Email": "ag3030@trevor.org",
        "EmailBad": false,
        "PublishEmail": true,
        "MyContactsID": 0,
        "HasRelationships": false,
        "GradYear": "2024",
        "Grade": "",
        "GradeDisplay": "Twelfth",
        "Department": "",
        "SpouseID": 0,
        "GradeNumeric": 0,
        "GradeNumericDisplay": "12",
        "TotalCount": 0,
        "Deceased": false,
        "IsStudentInd": false,
        "PreferredAddressId": 2006984,
        "PreferredAddressLat": 0.0,
        "PreferredAddressLng": 0.0,
        "JobTitle": ""
    },
    {
        "UserID": 5500901,
        "FirstName": "Jacob",
        "LastName": "Gelman",
        "PublishUserProfile": true,
        "LargeFileName": "large_user5500901_3834045_982.jpg",
        "Email": "jg4270@trevor.org",
        "EmailBad": false,
        "PublishEmail": true,
        "MyContactsID": 0,
        "HasRelationships": false,
        "Nickname": "Jakey",
        "GradYear": "2024",
        "Grade": "",
        "GradeDisplay": "Twelfth",
        "Department": "",
        "SpouseID": 0,
        "GradeNumeric": 0,
        "GradeNumericDisplay": "12",
        "TotalCount": 0,
        "Deceased": false,
        "IsStudentInd": false,
        "PreferredAddressId": 3956522,
        "PreferredAddressLat": 0.0,
        "PreferredAddressLng": 0.0,
        "JobTitle": ""
    },
    {
        "UserID": 5984343,
        "FirstName": "Jesse",
        "LastName": "Geoghan",
        "PublishUserProfile": true,
        "LargeFileName": "large_user5984343_4317249_112.jpg",
        "Email": "jg4409@trevor.org",
        "EmailBad": false,
        "PublishEmail": true,
        "MyContactsID": 0,
        "HasRelationships": false,
        "Nickname": "Jesse",
        "GradYear": "2024",
        "Grade": "",
        "GradeDisplay": "Twelfth",
        "Department": "",
        "SpouseID": 0,
        "GradeNumeric": 0,
        "GradeNumericDisplay": "12",
        "TotalCount": 0,
        "Deceased": false,
        "IsStudentInd": false,
        "PreferredAddressId": 4648776,
        "PreferredAddressLat": 0.0,
        "PreferredAddressLng": 0.0,
        "JobTitle": ""
    },
    {
        "UserID": 2833341,
        "FirstName": "Mikail",
        "LastName": "Ghani",
        "PublishUserProfile": true,
        "LargeFileName": "large_user2833341_1242233_349.jpg",
        "Email": "mg3255@trevor.org",
        "EmailBad": false,
        "PublishEmail": true,
        "MyContactsID": 0,
        "HasRelationships": false,
        "GradYear": "2024",
        "Grade": "",
        "GradeDisplay": "Twelfth",
        "Department": "",
        "SpouseID": 0,
        "GradeNumeric": 0,
        "GradeNumericDisplay": "12",
        "TotalCount": 0,
        "Deceased": false,
        "IsStudentInd": false,
        "PreferredAddressId": 2128441,
        "PreferredAddressLat": 0.0,
        "PreferredAddressLng": 0.0,
        "JobTitle": ""
    },
    {
        "UserID": 2728532,
        "FirstName": "Katherine",
        "LastName": "Giffler",
        "PublishUserProfile": true,
        "LargeFileName": "large_user2728532_1147114_773.jpg",
        "Email": "kg3178@trevor.org",
        "EmailBad": false,
        "PublishEmail": true,
        "MyContactsID": 0,
        "HasRelationships": false,
        "Nickname": "Kate",
        "GradYear": "2024",
        "Grade": "",
        "GradeDisplay": "Twelfth",
        "Department": "",
        "SpouseID": 0,
        "GradeNumeric": 0,
        "GradeNumericDisplay": "12",
        "TotalCount": 0,
        "Deceased": false,
        "IsStudentInd": false,
        "PreferredAddressId": 2052620,
        "PreferredAddressLat": 0.0,
        "PreferredAddressLng": 0.0,
        "JobTitle": ""
    },
    {
        "UserID": 5984345,
        "FirstName": "Julian",
        "LastName": "Glickman",
        "PublishUserProfile": true,
        "LargeFileName": "large_user5984345_4317251_494.jpg",
        "Email": "jg4419@trevor.org",
        "EmailBad": false,
        "PublishEmail": true,
        "MyContactsID": 0,
        "HasRelationships": false,
        "Nickname": "Julian",
        "GradYear": "2024",
        "Grade": "",
        "GradeDisplay": "Twelfth",
        "Department": "",
        "SpouseID": 0,
        "GradeNumeric": 0,
        "GradeNumericDisplay": "12",
        "TotalCount": 0,
        "Deceased": false,
        "IsStudentInd": false,
        "PreferredAddressId": 4648779,
        "PreferredAddressLat": 0.0,
        "PreferredAddressLng": 0.0,
        "JobTitle": ""
    },
    {
        "UserID": 5984358,
        "FirstName": "Sophie",
        "LastName": "Harris",
        "PublishUserProfile": true,
        "LargeFileName": "large_user5984358_4317264_325.jpg",
        "Email": "sh4438@trevor.org",
        "EmailBad": false,
        "PublishEmail": true,
        "MyContactsID": 0,
        "HasRelationships": false,
        "Nickname": "Sophie",
        "GradYear": "2024",
        "Grade": "",
        "GradeDisplay": "Twelfth",
        "Department": "",
        "SpouseID": 0,
        "GradeNumeric": 0,
        "GradeNumericDisplay": "12",
        "TotalCount": 0,
        "Deceased": false,
        "IsStudentInd": false,
        "PreferredAddressId": 4648781,
        "PreferredAddressLat": 0.0,
        "PreferredAddressLng": 0.0,
        "JobTitle": ""
    },
    {
        "UserID": 4397350,
        "FirstName": "Chloe",
        "LastName": "Hershkowitz",
        "PublishUserProfile": true,
        "LargeFileName": "large_user4397350_2732703_523.jpg",
        "Email": "ch4011@trevor.org",
        "EmailBad": false,
        "PublishEmail": true,
        "MyContactsID": 0,
        "HasRelationships": false,
        "Nickname": "Chloe",
        "GradYear": "2024",
        "Grade": "",
        "GradeDisplay": "Twelfth",
        "Department": "",
        "SpouseID": 0,
        "GradeNumeric": 0,
        "GradeNumericDisplay": "12",
        "TotalCount": 0,
        "Deceased": false,
        "IsStudentInd": false,
        "PreferredAddressId": 2052258,
        "PreferredAddressLat": 0.0,
        "PreferredAddressLng": 0.0,
        "JobTitle": ""
    },
    {
        "UserID": 6005223,
        "FirstName": "Conor",
        "LastName": "Hogan",
        "PublishUserProfile": true,
        "LargeFileName": "large_user6005223_4338105_838.jpg",
        "Email": "ch4445@trevor.org",
        "EmailBad": false,
        "PublishEmail": true,
        "MyContactsID": 0,
        "HasRelationships": false,
        "Nickname": "Conor",
        "GradYear": "2024",
        "Grade": "",
        "GradeDisplay": "Twelfth",
        "Department": "",
        "SpouseID": 0,
        "GradeNumeric": 0,
        "GradeNumericDisplay": "12",
        "TotalCount": 0,
        "Deceased": false,
        "IsStudentInd": false,
        "PreferredAddressId": 4405611,
        "PreferredAddressLat": 0.0,
        "PreferredAddressLng": 0.0,
        "JobTitle": ""
    },
    {
        "UserID": 4397353,
        "FirstName": "Naomi",
        "LastName": "Ihueze",
        "PublishUserProfile": true,
        "LargeFileName": "large_user4397353_2732706_542.jpg",
        "Email": "ni4026@trevor.org",
        "EmailBad": false,
        "PublishEmail": true,
        "MyContactsID": 0,
        "HasRelationships": false,
        "Nickname": "Naomi",
        "GradYear": "2024",
        "Grade": "",
        "GradeDisplay": "Twelfth",
        "Department": "",
        "SpouseID": 0,
        "GradeNumeric": 0,
        "GradeNumericDisplay": "12",
        "TotalCount": 0,
        "Deceased": false,
        "IsStudentInd": false,
        "PreferredAddressId": 2567715,
        "PreferredAddressLat": 0.0,
        "PreferredAddressLng": 0.0,
        "JobTitle": ""
    },
    {
        "UserID": 5984361,
        "FirstName": "Talia",
        "LastName": "Janevski",
        "PublishUserProfile": true,
        "LargeFileName": "large_user5984361_4317267_369.jpg",
        "Email": "tj4420@trevor.org",
        "EmailBad": false,
        "PublishEmail": true,
        "MyContactsID": 0,
        "HasRelationships": false,
        "Nickname": "Talia",
        "GradYear": "2024",
        "Grade": "",
        "GradeDisplay": "Twelfth",
        "Department": "",
        "SpouseID": 0,
        "GradeNumeric": 0,
        "GradeNumericDisplay": "12",
        "TotalCount": 0,
        "Deceased": false,
        "IsStudentInd": false,
        "PreferredAddressId": 4308775,
        "PreferredAddressLat": 0.0,
        "PreferredAddressLng": 0.0,
        "JobTitle": ""
    },
    {
        "UserID": 6014830,
        "FirstName": "Emma",
        "LastName": "Jose",
        "PublishUserProfile": true,
        "LargeFileName": "large_user6014830_4347680_449.jpg",
        "Email": "ej4446@trevor.org",
        "EmailBad": false,
        "PublishEmail": true,
        "MyContactsID": 0,
        "HasRelationships": false,
        "Nickname": "Emma",
        "GradYear": "2024",
        "Grade": "",
        "GradeDisplay": "Twelfth",
        "Department": "",
        "SpouseID": 0,
        "GradeNumeric": 0,
        "GradeNumericDisplay": "12",
        "TotalCount": 0,
        "Deceased": false,
        "IsStudentInd": false,
        "PreferredAddressId": 4648827,
        "PreferredAddressLat": 0.0,
        "PreferredAddressLng": 0.0,
        "JobTitle": ""
    },
    {
        "UserID": 5984364,
        "FirstName": "James",
        "LastName": "Karmacharya",
        "PublishUserProfile": true,
        "LargeFileName": "large_user5984364_4317270_463.jpg",
        "Email": "jk4363@trevor.org",
        "EmailBad": false,
        "PublishEmail": true,
        "MyContactsID": 0,
        "HasRelationships": false,
        "GradYear": "2024",
        "Grade": "",
        "GradeDisplay": "Twelfth",
        "Department": "",
        "SpouseID": 0,
        "GradeNumeric": 0,
        "GradeNumericDisplay": "12",
        "TotalCount": 0,
        "Deceased": false,
        "IsStudentInd": false,
        "PreferredAddressId": 4308777,
        "PreferredAddressLat": 0.0,
        "PreferredAddressLng": 0.0,
        "JobTitle": ""
    },
    {
        "UserID": 2833365,
        "FirstName": "Grace",
        "LastName": "Karr",
        "PublishUserProfile": true,
        "LargeFileName": "large_user2833365_1242252_680.jpg",
        "Email": "gk3274@trevor.org",
        "EmailBad": false,
        "PublishEmail": true,
        "MyContactsID": 0,
        "HasRelationships": false,
        "GradYear": "2024",
        "Grade": "",
        "GradeDisplay": "Twelfth",
        "Department": "",
        "SpouseID": 0,
        "GradeNumeric": 0,
        "GradeNumericDisplay": "12",
        "TotalCount": 0,
        "Deceased": false,
        "IsStudentInd": false,
        "PreferredAddressId": 2128481,
        "PreferredAddressLat": 0.0,
        "PreferredAddressLng": 0.0,
        "JobTitle": ""
    },
    {
        "UserID": 6362958,
        "FirstName": "Ryan",
        "LastName": "Kim",
        "PublishUserProfile": true,
        "LargeFileName": "large_user6362958_4695348_390.jpg",
        "Email": "rk4559@trevor.org",
        "EmailBad": false,
        "PublishEmail": true,
        "MyContactsID": 0,
        "HasRelationships": false,
        "Nickname": "Ryan",
        "GradYear": "2024",
        "Grade": "",
        "GradeDisplay": "Twelfth",
        "Department": "",
        "SpouseID": 0,
        "GradeNumeric": 0,
        "GradeNumericDisplay": "12",
        "TotalCount": 0,
        "Deceased": false,
        "IsStudentInd": false,
        "PreferredAddressId": 4532761,
        "PreferredAddressLat": 0.0,
        "PreferredAddressLng": 0.0,
        "JobTitle": ""
    },
    {
        "UserID": 4950180,
        "FirstName": "Emily",
        "LastName": "Koplin",
        "PublishUserProfile": true,
        "LargeFileName": "large_user4950180_3285016_759.jpg",
        "Email": "ek4142@trevor.org",
        "EmailBad": false,
        "PublishEmail": true,
        "MyContactsID": 0,
        "HasRelationships": false,
        "GradYear": "2024",
        "Grade": "",
        "GradeDisplay": "Twelfth",
        "Department": "",
        "SpouseID": 0,
        "GradeNumeric": 0,
        "GradeNumericDisplay": "12",
        "TotalCount": 0,
        "Deceased": false,
        "IsStudentInd": false,
        "PreferredAddressId": 3599831,
        "PreferredAddressLat": 0.0,
        "PreferredAddressLng": 0.0,
        "JobTitle": ""
    },
    {
        "UserID": 5984368,
        "FirstName": "Benjamin",
        "LastName": "Kramer",
        "PublishUserProfile": true,
        "LargeFileName": "large_user5984368_4317274_118.jpg",
        "Email": "bk4410@trevor.org",
        "EmailBad": false,
        "PublishEmail": true,
        "MyContactsID": 0,
        "HasRelationships": false,
        "Nickname": "Benjamin",
        "GradYear": "2024",
        "Grade": "",
        "GradeDisplay": "Twelfth",
        "Department": "",
        "SpouseID": 0,
        "GradeNumeric": 0,
        "GradeNumericDisplay": "12",
        "TotalCount": 0,
        "Deceased": false,
        "IsStudentInd": false,
        "PreferredAddressId": 4648859,
        "PreferredAddressLat": 0.0,
        "PreferredAddressLng": 0.0,
        "JobTitle": ""
    },
    {
        "UserID": 5984371,
        "FirstName": "Nathaniel",
        "LastName": "Kron",
        "PublishUserProfile": true,
        "LargeFileName": "large_user5984371_4317277_339.jpg",
        "Email": "nk4391@trevor.org",
        "EmailBad": false,
        "PublishEmail": true,
        "MyContactsID": 0,
        "HasRelationships": false,
        "Nickname": "Nate",
        "GradYear": "2024",
        "Grade": "",
        "GradeDisplay": "Twelfth",
        "Department": "",
        "SpouseID": 0,
        "GradeNumeric": 0,
        "GradeNumericDisplay": "12",
        "TotalCount": 0,
        "Deceased": false,
        "IsStudentInd": false,
        "PreferredAddressId": 4648981,
        "PreferredAddressLat": 0.0,
        "PreferredAddressLng": 0.0,
        "JobTitle": ""
    },
    {
        "UserID": 5984385,
        "FirstName": "Brandon",
        "LastName": "Lioudis",
        "PublishUserProfile": true,
        "LargeFileName": "large_user5984385_4317291_641.jpg",
        "Email": "bl4422@trevor.org",
        "EmailBad": false,
        "PublishEmail": true,
        "MyContactsID": 0,
        "HasRelationships": false,
        "GradYear": "2024",
        "Grade": "",
        "GradeDisplay": "Twelfth",
        "Department": "",
        "SpouseID": 0,
        "GradeNumeric": 0,
        "GradeNumericDisplay": "12",
        "TotalCount": 0,
        "Deceased": false,
        "IsStudentInd": false,
        "PreferredAddressId": 4649007,
        "PreferredAddressLat": 0.0,
        "PreferredAddressLng": 0.0,
        "JobTitle": ""
    },
    {
        "UserID": 5984388,
        "FirstName": "Justin",
        "LastName": "Lioudis",
        "PublishUserProfile": true,
        "LargeFileName": "large_user5984388_4317294_193.jpg",
        "Email": "jl4423@trevor.org",
        "EmailBad": false,
        "PublishEmail": true,
        "MyContactsID": 0,
        "HasRelationships": false,
        "GradYear": "2024",
        "Grade": "",
        "GradeDisplay": "Twelfth",
        "Department": "",
        "SpouseID": 0,
        "GradeNumeric": 0,
        "GradeNumericDisplay": "12",
        "TotalCount": 0,
        "Deceased": false,
        "IsStudentInd": false,
        "PreferredAddressId": 4649011,
        "PreferredAddressLat": 0.0,
        "PreferredAddressLng": 0.0,
        "JobTitle": ""
    },
    {
        "UserID": 2663810,
        "FirstName": "Arav",
        "LastName": "Malhotra",
        "PublishUserProfile": true,
        "LargeFileName": "large_user2663810_1091094_67.jpg",
        "Email": "am3043@trevor.org",
        "EmailBad": false,
        "PublishEmail": true,
        "MyContactsID": 0,
        "HasRelationships": false,
        "GradYear": "2024",
        "Grade": "",
        "GradeDisplay": "Twelfth",
        "Department": "",
        "SpouseID": 0,
        "GradeNumeric": 0,
        "GradeNumericDisplay": "12",
        "TotalCount": 0,
        "Deceased": false,
        "IsStudentInd": false,
        "PreferredAddressId": 2007056,
        "PreferredAddressLat": 0.0,
        "PreferredAddressLng": 0.0,
        "JobTitle": ""
    },
    {
        "UserID": 2663811,
        "FirstName": "Cooper",
        "LastName": "Mark",
        "PublishUserProfile": true,
        "LargeFileName": "large_user2663811_1091095_688.jpg",
        "Email": "cm3010@trevor.org",
        "EmailBad": false,
        "PublishEmail": true,
        "MyContactsID": 0,
        "HasRelationships": false,
        "GradYear": "2024",
        "Grade": "",
        "GradeDisplay": "Twelfth",
        "Department": "",
        "SpouseID": 0,
        "GradeNumeric": 0,
        "GradeNumericDisplay": "12",
        "TotalCount": 0,
        "Deceased": false,
        "IsStudentInd": false,
        "PreferredAddressId": 1794062,
        "PreferredAddressLat": 0.0,
        "PreferredAddressLng": 0.0,
        "JobTitle": ""
    },
    {
        "UserID": 5984396,
        "FirstName": "Michelle",
        "LastName": "Mesnick",
        "PublishUserProfile": true,
        "LargeFileName": "large_user5984396_4317302_772.jpg",
        "Email": "mm4425@trevor.org",
        "EmailBad": false,
        "PublishEmail": true,
        "MyContactsID": 0,
        "HasRelationships": false,
        "Nickname": "Michelle",
        "GradYear": "2024",
        "Grade": "",
        "GradeDisplay": "Twelfth",
        "Department": "",
        "SpouseID": 0,
        "GradeNumeric": 0,
        "GradeNumericDisplay": "12",
        "TotalCount": 0,
        "Deceased": false,
        "IsStudentInd": false,
        "PreferredAddressId": 4405323,
        "PreferredAddressLat": 0.0,
        "PreferredAddressLng": 0.0,
        "JobTitle": ""
    },
    {
        "UserID": 6426459,
        "FirstName": "Kira",
        "LastName": "Moses",
        "PublishUserProfile": true,
        "LargeFileName": "large_user6426459_4758744_265.jpg",
        "Email": "km4630@trevor.org",
        "EmailBad": false,
        "PublishEmail": true,
        "MyContactsID": 0,
        "HasRelationships": false,
        "GradYear": "2024",
        "Grade": "",
        "GradeDisplay": "Twelfth",
        "Department": "",
        "SpouseID": 0,
        "GradeNumeric": 0,
        "GradeNumericDisplay": "12",
        "TotalCount": 0,
        "Deceased": false,
        "IsStudentInd": false,
        "PreferredAddressId": 4621551,
        "PreferredAddressLat": 0.0,
        "PreferredAddressLng": 0.0,
        "JobTitle": ""
    },
    {
        "UserID": 5984402,
        "FirstName": "Anna",
        "LastName": "Natale",
        "PublishUserProfile": true,
        "LargeFileName": "large_user5984402_4317308_693.jpg",
        "Email": "an4404@trevor.org",
        "EmailBad": false,
        "PublishEmail": true,
        "MyContactsID": 0,
        "HasRelationships": false,
        "GradYear": "2024",
        "Grade": "",
        "GradeDisplay": "Twelfth",
        "Department": "",
        "SpouseID": 0,
        "GradeNumeric": 0,
        "GradeNumericDisplay": "12",
        "TotalCount": 0,
        "Deceased": false,
        "IsStudentInd": false,
        "PreferredAddressId": 4649014,
        "PreferredAddressLat": 0.0,
        "PreferredAddressLng": 0.0,
        "JobTitle": ""
    },
    {
        "UserID": 2728629,
        "FirstName": "Nathaniel",
        "LastName": "Nesci",
        "PublishUserProfile": true,
        "LargeFileName": "large_user2728629_1147206_240.jpg",
        "Email": "nn3147@trevor.org",
        "EmailBad": false,
        "PublishEmail": true,
        "MyContactsID": 0,
        "HasRelationships": false,
        "GradYear": "2024",
        "Grade": "",
        "GradeDisplay": "Twelfth",
        "Department": "",
        "SpouseID": 0,
        "GradeNumeric": 0,
        "GradeNumericDisplay": "12",
        "TotalCount": 0,
        "Deceased": false,
        "IsStudentInd": false,
        "PreferredAddressId": 1794180,
        "PreferredAddressLat": 0.0,
        "PreferredAddressLng": 0.0,
        "JobTitle": ""
    },
    {
        "UserID": 3471931,
        "FirstName": "Finlay",
        "LastName": "Nicklin",
        "PublishUserProfile": true,
        "LargeFileName": "large_user3471931_1862492_259.jpg",
        "Email": "fn3846@trevor.org",
        "EmailBad": false,
        "PublishEmail": true,
        "MyContactsID": 0,
        "HasRelationships": false,
        "Nickname": "Finlay",
        "GradYear": "2024",
        "Grade": "",
        "GradeDisplay": "Twelfth",
        "Department": "",
        "SpouseID": 0,
        "GradeNumeric": 0,
        "GradeNumericDisplay": "12",
        "TotalCount": 0,
        "Deceased": false,
        "IsStudentInd": false,
        "PreferredAddressId": 3737754,
        "PreferredAddressLat": 0.0,
        "PreferredAddressLng": 0.0,
        "JobTitle": ""
    },
    {
        "UserID": 5984407,
        "FirstName": "Eva",
        "LastName": "Osborne",
        "PublishUserProfile": true,
        "LargeFileName": "large_user5984407_4317313_53.jpg",
        "Email": "eo4406@trevor.org",
        "EmailBad": false,
        "PublishEmail": true,
        "MyContactsID": 0,
        "HasRelationships": false,
        "Nickname": "Eva",
        "GradYear": "2024",
        "Grade": "",
        "GradeDisplay": "Twelfth",
        "Department": "",
        "SpouseID": 0,
        "GradeNumeric": 0,
        "GradeNumericDisplay": "12",
        "TotalCount": 0,
        "Deceased": false,
        "IsStudentInd": false,
        "PreferredAddressId": 4309109,
        "PreferredAddressLat": 0.0,
        "PreferredAddressLng": 0.0,
        "JobTitle": ""
    },
    {
        "UserID": 6459102,
        "FirstName": "Evan",
        "LastName": "Ostrander",
        "PublishUserProfile": true,
        "LargeFileName": "large_user6459102_4791344_933.jpg",
        "Email": "eo4635@trevor.org",
        "EmailBad": false,
        "PublishEmail": true,
        "MyContactsID": 0,
        "HasRelationships": false,
        "GradYear": "2024",
        "Grade": "",
        "GradeDisplay": "Twelfth",
        "Department": "",
        "SpouseID": 0,
        "GradeNumeric": 0,
        "GradeNumericDisplay": "12",
        "TotalCount": 0,
        "Deceased": false,
        "IsStudentInd": false,
        "PreferredAddressId": 4560079,
        "PreferredAddressLat": 0.0,
        "PreferredAddressLng": 0.0,
        "JobTitle": ""
    },
    {
        "UserID": 2663838,
        "FirstName": "Anouk",
        "LastName": "Payot",
        "PublishUserProfile": true,
        "LargeFileName": "large_user2663838_1091116_193.jpg",
        "Email": "ap3013@trevor.org",
        "EmailBad": false,
        "PublishEmail": true,
        "MyContactsID": 0,
        "HasRelationships": false,
        "GradYear": "2024",
        "Grade": "",
        "GradeDisplay": "Twelfth",
        "Department": "",
        "SpouseID": 0,
        "GradeNumeric": 0,
        "GradeNumericDisplay": "12",
        "TotalCount": 0,
        "Deceased": false,
        "IsStudentInd": false,
        "PreferredAddressId": 1794246,
        "PreferredAddressLat": 0.0,
        "PreferredAddressLng": 0.0,
        "JobTitle": ""
    },
    {
        "UserID": 2833401,
        "FirstName": "Danah",
        "LastName": "Plair",
        "PublishUserProfile": true,
        "LargeFileName": "large_user2833401_1242275_67.jpg",
        "Email": "dp3270@trevor.org",
        "EmailBad": false,
        "PublishEmail": true,
        "MyContactsID": 0,
        "HasRelationships": false,
        "GradYear": "2024",
        "Grade": "",
        "GradeDisplay": "Twelfth",
        "Department": "",
        "SpouseID": 0,
        "GradeNumeric": 0,
        "GradeNumericDisplay": "12",
        "TotalCount": 0,
        "Deceased": false,
        "IsStudentInd": false,
        "PreferredAddressId": 2128597,
        "PreferredAddressLat": 0.0,
        "PreferredAddressLng": 0.0,
        "JobTitle": ""
    },
    {
        "UserID": 2833407,
        "FirstName": "Aaron",
        "LastName": "Rodricks",
        "PublishUserProfile": true,
        "LargeFileName": "large_user2833407_1242280_460.jpg",
        "Email": "ar3260@trevor.org",
        "EmailBad": false,
        "PublishEmail": true,
        "MyContactsID": 0,
        "HasRelationships": false,
        "GradYear": "2024",
        "Grade": "",
        "GradeDisplay": "Twelfth",
        "Department": "",
        "SpouseID": 0,
        "GradeNumeric": 0,
        "GradeNumericDisplay": "12",
        "TotalCount": 0,
        "Deceased": false,
        "IsStudentInd": false,
        "PreferredAddressId": 2128550,
        "PreferredAddressLat": 0.0,
        "PreferredAddressLng": 0.0,
        "JobTitle": ""
    },
    {
        "UserID": 4397373,
        "FirstName": "Maya",
        "LastName": "Rothbard",
        "PublishUserProfile": true,
        "LargeFileName": "large_user4397373_2732726_456.jpg",
        "Email": "mr4035@trevor.org",
        "EmailBad": false,
        "PublishEmail": true,
        "MyContactsID": 0,
        "HasRelationships": false,
        "Nickname": "Maya",
        "GradYear": "2024",
        "Grade": "",
        "GradeDisplay": "Twelfth",
        "Department": "",
        "SpouseID": 0,
        "GradeNumeric": 0,
        "GradeNumericDisplay": "12",
        "TotalCount": 0,
        "Deceased": false,
        "IsStudentInd": false,
        "PreferredAddressId": 3243899,
        "PreferredAddressLat": 0.0,
        "PreferredAddressLng": 0.0,
        "JobTitle": ""
    },
    {
        "UserID": 5984413,
        "FirstName": "Kalina",
        "LastName": "Sabala Montes",
        "PublishUserProfile": true,
        "LargeFileName": "large_user5984413_4317319_951.jpg",
        "Email": "ks4427@trevor.org",
        "EmailBad": false,
        "PublishEmail": true,
        "MyContactsID": 0,
        "HasRelationships": false,
        "GradYear": "2024",
        "Grade": "",
        "GradeDisplay": "Twelfth",
        "Department": "",
        "SpouseID": 0,
        "GradeNumeric": 0,
        "GradeNumericDisplay": "12",
        "TotalCount": 0,
        "Deceased": false,
        "IsStudentInd": false,
        "PreferredAddressId": 4455908,
        "PreferredAddressLat": 0.0,
        "PreferredAddressLng": 0.0,
        "JobTitle": ""
    },
    {
        "UserID": 2749272,
        "FirstName": "Leon",
        "LastName": "Schaumann",
        "PublishUserProfile": true,
        "LargeFileName": "large_user2749272_1164776_263.jpg",
        "Email": "ls3205@trevor.org",
        "EmailBad": false,
        "PublishEmail": true,
        "HomePhone": "(212) 722-3326                ",
        "MyContactsID": 0,
        "HasRelationships": true,
        "GradYear": "2024",
        "Grade": "",
        "GradeDisplay": "Twelfth",
        "Department": "",
        "SpouseID": 0,
        "GradeNumeric": 0,
        "GradeNumericDisplay": "12",
        "TotalCount": 0,
        "Deceased": false,
        "IsStudentInd": false,
        "PreferredAddressId": 2070075,
        "PreferredAddressLat": 0.0,
        "PreferredAddressLng": 0.0,
        "JobTitle": ""
    },
    {
        "UserID": 2663853,
        "FirstName": "Zoe",
        "LastName": "Schnitzer",
        "PublishUserProfile": true,
        "LargeFileName": "large_user2663853_1091128_65.jpg",
        "Email": "zs2927@trevor.org",
        "EmailBad": false,
        "PublishEmail": true,
        "MyContactsID": 0,
        "HasRelationships": false,
        "GradYear": "2024",
        "Grade": "",
        "GradeDisplay": "Twelfth",
        "Department": "",
        "SpouseID": 0,
        "GradeNumeric": 0,
        "GradeNumericDisplay": "12",
        "TotalCount": 0,
        "Deceased": false,
        "IsStudentInd": false,
        "PreferredAddressId": 1794394,
        "PreferredAddressLat": 0.0,
        "PreferredAddressLng": 0.0,
        "JobTitle": ""
    },
    {
        "UserID": 6040283,
        "FirstName": "Jessica",
        "LastName": "Silverman",
        "PublishUserProfile": true,
        "LargeFileName": "large_user6040283_4373058_824.jpg",
        "Email": "js4455@trevor.org",
        "EmailBad": false,
        "PublishEmail": true,
        "MyContactsID": 0,
        "HasRelationships": false,
        "Nickname": "Jessie",
        "GradYear": "2024",
        "Grade": "",
        "GradeDisplay": "Twelfth",
        "Department": "",
        "SpouseID": 0,
        "GradeNumeric": 0,
        "GradeNumericDisplay": "12",
        "TotalCount": 0,
        "Deceased": false,
        "IsStudentInd": false,
        "PreferredAddressId": 4649015,
        "PreferredAddressLat": 0.0,
        "PreferredAddressLng": 0.0,
        "JobTitle": ""
    },
    {
        "UserID": 2833418,
        "FirstName": "Makela",
        "LastName": "Simpson",
        "PublishUserProfile": true,
        "LargeFileName": "large_user2833418_1242284_336.jpg",
        "Email": "ms3275@trevor.org",
        "EmailBad": false,
        "PublishEmail": true,
        "MyContactsID": 0,
        "HasRelationships": false,
        "GradYear": "2024",
        "Grade": "",
        "GradeDisplay": "Twelfth",
        "Department": "",
        "SpouseID": 0,
        "GradeNumeric": 0,
        "GradeNumericDisplay": "12",
        "TotalCount": 0,
        "Deceased": false,
        "IsStudentInd": false,
        "PreferredAddressId": 2128502,
        "PreferredAddressLat": 0.0,
        "PreferredAddressLng": 0.0,
        "JobTitle": ""
    },
    {
        "UserID": 4397379,
        "FirstName": "Amara",
        "LastName": "Singer",
        "PublishUserProfile": true,
        "LargeFileName": "large_user4397379_2732732_708.jpg",
        "Email": "rs4017@trevor.org",
        "EmailBad": false,
        "PublishEmail": true,
        "MyContactsID": 0,
        "HasRelationships": false,
        "Nickname": "Mari",
        "GradYear": "2024",
        "Grade": "",
        "GradeDisplay": "Twelfth",
        "Department": "",
        "SpouseID": 0,
        "GradeNumeric": 0,
        "GradeNumericDisplay": "12",
        "TotalCount": 0,
        "Deceased": false,
        "IsStudentInd": false,
        "PreferredAddressId": 3243905,
        "PreferredAddressLat": 0.0,
        "PreferredAddressLng": 0.0,
        "JobTitle": ""
    },
    {
        "UserID": 5984416,
        "FirstName": "Chiara",
        "LastName": "Smith",
        "PublishUserProfile": true,
        "LargeFileName": "large_user5984416_4317322_613.jpg",
        "Email": "cs4428@trevor.org",
        "EmailBad": false,
        "PublishEmail": true,
        "MyContactsID": 0,
        "HasRelationships": false,
        "Nickname": "Chiara",
        "GradYear": "2024",
        "Grade": "",
        "GradeDisplay": "Twelfth",
        "Department": "",
        "SpouseID": 0,
        "GradeNumeric": 0,
        "GradeNumericDisplay": "12",
        "TotalCount": 0,
        "Deceased": false,
        "IsStudentInd": false,
        "PreferredAddressId": 4649017,
        "PreferredAddressLat": 0.0,
        "PreferredAddressLng": 0.0,
        "JobTitle": ""
    },
    {
        "UserID": 2833424,
        "FirstName": "Leo",
        "LastName": "Sondik",
        "PublishUserProfile": true,
        "LargeFileName": "large_user2833424_1242288_437.jpeg",
        "Email": "ls3245@trevor.org",
        "EmailBad": false,
        "PublishEmail": true,
        "MyContactsID": 0,
        "HasRelationships": false,
        "GradYear": "2024",
        "Grade": "",
        "GradeDisplay": "Twelfth",
        "Department": "",
        "SpouseID": 0,
        "GradeNumeric": 0,
        "GradeNumericDisplay": "12",
        "TotalCount": 0,
        "Deceased": false,
        "IsStudentInd": false,
        "PreferredAddressId": 2128578,
        "PreferredAddressLat": 0.0,
        "PreferredAddressLng": 0.0,
        "JobTitle": ""
    },
    {
        "UserID": 5984419,
        "FirstName": "Jillian",
        "LastName": "Stahl",
        "PublishUserProfile": true,
        "LargeFileName": "large_user5984419_4317325_109.jpg",
        "Email": "js4429@trevor.org",
        "EmailBad": false,
        "PublishEmail": true,
        "MyContactsID": 0,
        "HasRelationships": false,
        "Nickname": "Jillian",
        "GradYear": "2024",
        "Grade": "",
        "GradeDisplay": "Twelfth",
        "Department": "",
        "SpouseID": 0,
        "GradeNumeric": 0,
        "GradeNumericDisplay": "12",
        "TotalCount": 0,
        "Deceased": false,
        "IsStudentInd": false,
        "PreferredAddressId": 4649023,
        "PreferredAddressLat": 0.0,
        "PreferredAddressLng": 0.0,
        "JobTitle": ""
    },
    {
        "UserID": 5984422,
        "FirstName": "Ava",
        "LastName": "Steiner",
        "PublishUserProfile": true,
        "LargeFileName": "large_user5984422_4317328_392.jpg",
        "Email": "as4411@trevor.org",
        "EmailBad": false,
        "PublishEmail": true,
        "MyContactsID": 0,
        "HasRelationships": false,
        "GradYear": "2024",
        "Grade": "",
        "GradeDisplay": "Twelfth",
        "Department": "",
        "SpouseID": 0,
        "GradeNumeric": 0,
        "GradeNumericDisplay": "12",
        "TotalCount": 0,
        "Deceased": false,
        "IsStudentInd": false,
        "PreferredAddressId": 4649028,
        "PreferredAddressLat": 0.0,
        "PreferredAddressLng": 0.0,
        "JobTitle": ""
    },
    {
        "UserID": 5984429,
        "FirstName": "Oliver",
        "LastName": "Strassberg",
        "PublishUserProfile": true,
        "LargeFileName": "large_user5984429_4317335_665.jpg",
        "Email": "os4430@trevor.org",
        "EmailBad": false,
        "PublishEmail": true,
        "MyContactsID": 0,
        "HasRelationships": false,
        "Nickname": "Oliver",
        "GradYear": "2024",
        "Grade": "",
        "GradeDisplay": "Twelfth",
        "Department": "",
        "SpouseID": 0,
        "GradeNumeric": 0,
        "GradeNumericDisplay": "12",
        "TotalCount": 0,
        "Deceased": false,
        "IsStudentInd": false,
        "PreferredAddressId": 4649030,
        "PreferredAddressLat": 0.0,
        "PreferredAddressLng": 0.0,
        "JobTitle": ""
    },
    {
        "UserID": 4397354,
        "FirstName": "Jude",
        "LastName": "Tehrani",
        "PublishUserProfile": true,
        "LargeFileName": "large_user4397354_2732707_853.jpg",
        "Email": "jt3976@trevor.org",
        "EmailBad": false,
        "PublishEmail": true,
        "MyContactsID": 0,
        "HasRelationships": false,
        "Nickname": "Jude",
        "GradYear": "2024",
        "Grade": "",
        "GradeDisplay": "Twelfth",
        "Department": "",
        "SpouseID": 0,
        "GradeNumeric": 0,
        "GradeNumericDisplay": "12",
        "TotalCount": 0,
        "Deceased": false,
        "IsStudentInd": false,
        "PreferredAddressId": 3081623,
        "PreferredAddressLat": 0.0,
        "PreferredAddressLng": 0.0,
        "JobTitle": ""
    },
    {
        "UserID": 3603697,
        "FirstName": "Hudson",
        "LastName": "Tesch",
        "PublishUserProfile": true,
        "LargeFileName": "large_user3603697_1988802.jpg",
        "Email": "ht3858@trevor.org",
        "EmailBad": false,
        "PublishEmail": true,
        "MyContactsID": 0,
        "HasRelationships": false,
        "GradYear": "2024",
        "Grade": "",
        "GradeDisplay": "Twelfth",
        "Department": "",
        "SpouseID": 0,
        "GradeNumeric": 0,
        "GradeNumericDisplay": "12",
        "TotalCount": 0,
        "Deceased": false,
        "IsStudentInd": false,
        "PreferredAddressId": 2768226,
        "PreferredAddressLat": 0.0,
        "PreferredAddressLng": 0.0,
        "JobTitle": ""
    },
    {
        "UserID": 4483664,
        "FirstName": "Maxwell",
        "LastName": "Turtz",
        "PublishUserProfile": true,
        "LargeFileName": "large_user4483664_2819005_455.jpg",
        "Email": "mt4066@trevor.org",
        "EmailBad": false,
        "PublishEmail": true,
        "MyContactsID": 0,
        "HasRelationships": false,
        "Nickname": "Max",
        "GradYear": "2024",
        "Grade": "",
        "GradeDisplay": "Twelfth",
        "Department": "",
        "SpouseID": 0,
        "GradeNumeric": 0,
        "GradeNumericDisplay": "12",
        "TotalCount": 0,
        "Deceased": false,
        "IsStudentInd": false,
        "PreferredAddressId": 3736014,
        "PreferredAddressLat": 0.0,
        "PreferredAddressLng": 0.0,
        "JobTitle": ""
    },
    {
        "UserID": 7288551,
        "FirstName": "Johannes",
        "LastName": "von Uexkull",
        "PublishUserProfile": true,
        "LargeFileName": "large_user7288551_5622145_459.jpg",
        "Email": "jv4883@trevor.org",
        "EmailBad": false,
        "PublishEmail": true,
        "MyContactsID": 0,
        "HasRelationships": false,
        "Nickname": "Johannes",
        "GradYear": "2024",
        "Grade": "",
        "GradeDisplay": "Twelfth",
        "Department": "",
        "SpouseID": 0,
        "GradeNumeric": 0,
        "GradeNumericDisplay": "12",
        "TotalCount": 0,
        "Deceased": false,
        "IsStudentInd": false,
        "PreferredAddressId": 5100084,
        "PreferredAddressLat": 0.0,
        "PreferredAddressLng": 0.0,
        "JobTitle": ""
    },
    {
        "UserID": 6830113,
        "FirstName": "Liam",
        "LastName": "Walsh",
        "PublishUserProfile": true,
        "LargeFileName": "large_user6830113_5164158_53.jpg",
        "Email": "lw4412@trevor.org",
        "EmailBad": false,
        "PublishEmail": true,
        "MyContactsID": 0,
        "HasRelationships": false,
        "Nickname": "Liam",
        "GradYear": "2024",
        "Grade": "",
        "GradeDisplay": "Twelfth",
        "Department": "",
        "SpouseID": 0,
        "GradeNumeric": 0,
        "GradeNumericDisplay": "12",
        "TotalCount": 0,
        "Deceased": false,
        "IsStudentInd": false,
        "PreferredAddressId": 5044786,
        "PreferredAddressLat": 0.0,
        "PreferredAddressLng": 0.0,
        "JobTitle": ""
    },
    {
        "UserID": 3942885,
        "FirstName": "Xiaotong",
        "LastName": "Wang",
        "PublishUserProfile": true,
        "LargeFileName": "large_user3942885_2279621_686.jpg",
        "Email": "ww3954@trevor.org",
        "EmailBad": false,
        "PublishEmail": true,
        "MyContactsID": 0,
        "HasRelationships": false,
        "Nickname": "Wanda",
        "GradYear": "2024",
        "Grade": "",
        "GradeDisplay": "Twelfth",
        "Department": "",
        "SpouseID": 0,
        "GradeNumeric": 0,
        "GradeNumericDisplay": "12",
        "TotalCount": 0,
        "Deceased": false,
        "IsStudentInd": false,
        "PreferredAddressId": 3097328,
        "PreferredAddressLat": 0.0,
        "PreferredAddressLng": 0.0,
        "JobTitle": ""
    },
    {
        "UserID": 2833437,
        "FirstName": "Neil",
        "LastName": "Weinberger",
        "PublishUserProfile": true,
        "LargeFileName": "large_user2833437_1242298_110.jpg",
        "Email": "nw3224@trevor.org",
        "EmailBad": false,
        "PublishEmail": true,
        "MyContactsID": 0,
        "HasRelationships": false,
        "GradYear": "2024",
        "Grade": "",
        "GradeDisplay": "Twelfth",
        "Department": "",
        "SpouseID": 0,
        "GradeNumeric": 0,
        "GradeNumericDisplay": "12",
        "TotalCount": 0,
        "Deceased": false,
        "IsStudentInd": false,
        "PreferredAddressId": 2128601,
        "PreferredAddressLat": 0.0,
        "PreferredAddressLng": 0.0,
        "JobTitle": ""
    },
    {
        "UserID": 5984433,
        "FirstName": "Alexandra",
        "LastName": "Weingard",
        "PublishUserProfile": true,
        "LargeFileName": "large_user5984433_4317339_757.jpg",
        "Email": "aw4433@trevor.org",
        "EmailBad": false,
        "PublishEmail": true,
        "MyContactsID": 0,
        "HasRelationships": false,
        "Nickname": "Alexandra",
        "GradYear": "2024",
        "Grade": "",
        "GradeDisplay": "Twelfth",
        "Department": "",
        "SpouseID": 0,
        "GradeNumeric": 0,
        "GradeNumericDisplay": "12",
        "TotalCount": 0,
        "Deceased": false,
        "IsStudentInd": false,
        "PreferredAddressId": 4909118,
        "PreferredAddressLat": 0.0,
        "PreferredAddressLng": 0.0,
        "JobTitle": ""
    },
    {
        "UserID": 6399640,
        "FirstName": "Dylan",
        "LastName": "Woods",
        "PublishUserProfile": true,
        "LargeFileName": "large_user6399640_4731976_202.jpg",
        "Email": "dw4432@trevor.org",
        "EmailBad": false,
        "PublishEmail": true,
        "MyContactsID": 0,
        "HasRelationships": false,
        "Nickname": "Dylan",
        "GradYear": "2024",
        "Grade": "",
        "GradeDisplay": "Twelfth",
        "Department": "",
        "SpouseID": 0,
        "GradeNumeric": 0,
        "GradeNumericDisplay": "12",
        "TotalCount": 0,
        "Deceased": false,
        "IsStudentInd": false,
        "PreferredAddressId": 4553921,
        "PreferredAddressLat": 0.0,
        "PreferredAddressLng": 0.0,
        "JobTitle": ""
    },
    {
        "UserID": 3427746,
        "FirstName": "Dylan",
        "LastName": "Yohai",
        "PublishUserProfile": true,
        "LargeFileName": "large_user3427746_1818307_425.jpg",
        "Email": "dy3772@trevor.org",
        "EmailBad": false,
        "PublishEmail": true,
        "MyContactsID": 0,
        "HasRelationships": false,
        "Nickname": "Dylan",
        "GradYear": "2024",
        "Grade": "",
        "GradeDisplay": "Twelfth",
        "Department": "",
        "SpouseID": 0,
        "GradeNumeric": 0,
        "GradeNumericDisplay": "12",
        "TotalCount": 0,
        "Deceased": false,
        "IsStudentInd": false,
        "PreferredAddressId": 2295557,
        "PreferredAddressLat": 0.0,
        "PreferredAddressLng": 0.0,
        "JobTitle": ""
    }
]